<Assemblies Version="620756994">
  <Assembly Name="Spring.Data, Version=1.1.0.2, Culture=neutral, PublicKeyToken=65e474d141e25e07" Cache="8187ecd9-05dd-4f2d-8459-7b23062dc9ef.ReflectionCache" Timestamp="633010006800000000" />
  <Assembly Name="Spring.Core, Version=1.1.0.2, Culture=neutral, PublicKeyToken=65e474d141e25e07" Cache="87e23ed4-936b-4c97-86bd-e1ecc3ce840c.ReflectionCache" Timestamp="633010006760000000" />
  <Assembly Name="Spring.Aop, Version=1.1.0.2, Culture=neutral, PublicKeyToken=65e474d141e25e07" Cache="de9d598b-de71-4f24-b59d-644bede2a7d3.ReflectionCache" Timestamp="633010006780000000" />
  <Assembly Name="Common.Logging, Version=1.1.0.2, Culture=neutral, PublicKeyToken=65e474d141e25e07" Cache="57512285-49e9-450b-95eb-6be941eb4c23.ReflectionCache" Timestamp="633004394460000000" />
  <Assembly Name="System.Data.SqlServerCe, Version=9.0.242.0, Culture=neutral, PublicKeyToken=89845dcd8080cc91" Cache="6a9a4920-4af5-4d79-88d0-d9750e023e15.ReflectionCache" Timestamp="632613476440000000" />
  <Assembly Name="antlr.runtime, Version=2.7.6.2, Culture=neutral, PublicKeyToken=65e474d141e25e07" Cache="40c21d0e-c15b-480f-9c0c-b742482ad671.ReflectionCache" Timestamp="632900468920000000" />
  <Assembly Name="Spring.Services, Version=1.1.0.2, Culture=neutral, PublicKeyToken=65e474d141e25e07" Cache="3496d5ec-f981-4bdb-b8ce-9fe0c913554d.ReflectionCache" Timestamp="633010006800000000" />
  <Assembly Name="Castle.ActiveRecord, Version=0.0.1.7, Culture=neutral, PublicKeyToken=407dd0808d44fbdc" Cache="b11e27f7-7532-4657-8b9d-a6d52ffcac14.ReflectionCache" Timestamp="632717630440000000" />
  <Assembly Name="Castle.ActiveRecord.Generator.Components, Version=0.0.1.6, Culture=neutral, PublicKeyToken=407dd0808d44fbdc" Cache="9fb8bb32-803f-4ddd-8870-c2a693293051.ReflectionCache" Timestamp="632717630940000000" />
  <Assembly Name="NHibernate, Version=1.2.0.3001, Culture=neutral, PublicKeyToken=aa95f207798dfdb4" Cache="eb349985-6721-4764-a39e-6473fcef0d54.ReflectionCache" Timestamp="633077774020000000" />
  <Assembly Name="ICSharpCode.SharpZipLib, Version=0.85.1.271, Culture=neutral, PublicKeyToken=1b03e6acf1164f73" Cache="f38ad4f6-3187-434a-93ea-4e7ffd85bd6c.ReflectionCache" Timestamp="633022720580000000" />
  <Assembly Name="NHibernate.Generics, Version=1.0.12.0, Culture=neutral, PublicKeyToken=null" Cache="c8b5e857-68c4-4638-830c-6fbfbabd025c.ReflectionCache" Timestamp="633009485420000000" />
  <Assembly Name="NHibernate.Generics, Version=1.0.12.0, Culture=neutral" Cache="48b1670d-df80-4cd4-8369-cd7567bdf367.ReflectionCache" Timestamp="633009485420000000" />
  <Assembly Name="MySql.Data, Version=5.0.5.0, Culture=neutral, PublicKeyToken=c5687fc88969c44d" Cache="ac643f1a-420b-41fc-b77a-4f99a3f80ab1.ReflectionCache" Timestamp="633087182760000000" />
  <Assembly Name="log4net, Version=1.2.10.0, Culture=neutral, PublicKeyToken=1b44e1d426115821" Cache="feb5601e-d61c-432e-8c57-6c38d52c6358.ReflectionCache" Timestamp="632793434680000000" />
</Assemblies>